ineedproxy/__init__.py
ineedproxy/data_manager.py
ineedproxy/file_ops.py
ineedproxy/get.py
ineedproxy/logger.py
ineedproxy/manager.py
ineedproxy/test_proxies.py
ineedproxy/utils.py
ineedproxy/version.py
ineedproxy-0.1.3.dist-info/licenses/LICENSE.md
ineedproxy-0.1.3.dist-info/METADATA
ineedproxy-0.1.3.dist-info/WHEEL
ineedproxy-0.1.3.dist-info/top_level.txt
ineedproxy-0.1.3.dist-info/RECORD
