Metadata-Version: 2.4
Name: ineedproxy
Version: 0.1.3
Summary: An aio library designed for easy and reliable access to working proxies. It primarily fetches, manages, rotates, and stores proxy data.
Home-page: https://github.com/paul-hartwich/ineedproxy
Author: Paul Hartwich
Author-email: paulnoahhartwich@gmail.com
License: MIT
Classifier: Programming Language :: Python :: 3
Classifier: License :: OSI Approved :: MIT License
Classifier: Operating System :: OS Independent
License-File: LICENSE.md
Requires-Dist: aiohttp~=3.11.11
Requires-Dist: msgpack~=1.1.0
Requires-Dist: orjson~=3.10.15
Requires-Dist: brotli
Dynamic: author
Dynamic: classifier
Dynamic: description
Dynamic: description-content-type
Dynamic: home-page
Dynamic: license
Dynamic: license-file
Dynamic: requires-dist
Dynamic: summary
